seagulls/rpg_demo/__init__.py
seagulls/rpg_demo/_character.py
seagulls/rpg_demo/_cli_command.py
seagulls/rpg_demo/_cli_entry_point.py
seagulls/rpg_demo/_cli_plugin.py
seagulls/rpg_demo/_di_container.py
seagulls/rpg_demo/_rpg_background.py
seagulls/rpg_demo/_rpg_scene.py
seagulls/rpg_demo/py.typed
seagulls_rpg_demo-0.1.0rc1.dist-info/entry_points.txt
seagulls_rpg_demo-0.1.0rc1.dist-info/WHEEL
seagulls_rpg_demo-0.1.0rc1.dist-info/METADATA
seagulls_rpg_demo-0.1.0rc1.dist-info/RECORD
